.gitignore
.prospector.yaml
.pylintrc
LICENSE
MANIFEST.in
README.rst
requirements.txt
run.sh
setup.cfg
setup.py
versioneer.py
qworker_sample/__init__.py
qworker_sample/_version.py
qworker_sample/qstask.py
qworker_sample/settings.py
qworker_sample/tasks.py
qworker_sample.egg-info/PKG-INFO
qworker_sample.egg-info/SOURCES.txt
qworker_sample.egg-info/dependency_links.txt
qworker_sample.egg-info/entry_points.txt
qworker_sample.egg-info/not-zip-safe
qworker_sample.egg-info/pbr.json
qworker_sample.egg-info/requires.txt
qworker_sample.egg-info/top_level.txt
qworker_sample/_cfgtool/install
qworker_sample/_cfgtool/qworker_sample
qworker_sample/_cfgtool/qworker_sample.conf.templ