Metadata-Version: 1.0
Name: qworker-sample
Version: 0.1.post8
Summary: Sample plugin workerd for QWorkerD
Home-page: UNKNOWN
Author: J C Lawrence
Author-email: claw@kanga.nu
License: LGPL v3.0
Platform: UNKNOWN
